<?xml version="1.0" encoding="utf-8"?>
<WordDefinition xmlns:xsi="http://www.w3.org/2001/XMLSchema-instance" xmlns:xsd="http://www.w3.org/2001/XMLSchema" xmlns="http://services.aonaware.com/webservices/">
  <Word>crusader</Word>
  <Definitions>
    <Definition>
      <Word>crusader</Word>
      <Dictionary>
        <Id>gcide</Id>
        <Name>The Collaborative International Dictionary of English v.0.44</Name>
      </Dictionary>
      <WordDefinition>Crusader \Cru*sad"er\ (-s?"d?r), n.
   One engaged in a crusade; as, the crusaders of the Middle
   Ages.
   [1913 Webster]

         Azure-eyed and golden-haired,
         Forth the young crusaders fared.         --Longfellow.
   [1913 Webster]
</WordDefinition>
    </Definition>
    <Definition>
      <Word>crusader</Word>
      <Dictionary>
        <Id>wn</Id>
        <Name>WordNet (r) 2.0</Name>
      </Dictionary>
      <WordDefinition>crusader
     n 1: a disputant who advocates reform [syn: {reformer}, {reformist},
           {meliorist}]
     2: a warrior who engages in a holy war; "the crusaders tried to
        recapture the Holy Land from the Muslims"
</WordDefinition>
    </Definition>
  </Definitions>
</WordDefinition>
