<?xml version="1.0" encoding="utf-8"?>
<WordDefinition xmlns:xsi="http://www.w3.org/2001/XMLSchema-instance" xmlns:xsd="http://www.w3.org/2001/XMLSchema" xmlns="http://services.aonaware.com/webservices/">
  <Word>beau</Word>
  <Definitions>
    <Definition>
      <Word>beau</Word>
      <Dictionary>
        <Id>gcide</Id>
        <Name>The Collaborative International Dictionary of English v.0.44</Name>
      </Dictionary>
      <WordDefinition>Beau \Beau\ (b[=o]), n.; pl. F. {Beaux} (E. pron. b[=o]z), E.
   {Beaus} (b[=o]z). [F., a fop, fr. beau fine, beautiful, fr.
   L. bellus pretty, fine, for bonulus, dim. of bonus good. See
   {Bounty}, and cf. {Belle}, {Beauty}.]
   1. A man who takes great care to dress in the latest fashion;
      a dandy.
      [1913 Webster]

   2. A man who escorts, or pays attentions to, a lady; an
      escort; a suitor or lover.
      [1913 Webster]
</WordDefinition>
    </Definition>
    <Definition>
      <Word>beau</Word>
      <Dictionary>
        <Id>wn</Id>
        <Name>WordNet (r) 2.0</Name>
      </Dictionary>
      <WordDefinition>beau
     n 1: a man who is the lover of a girl or young woman; "if I'd
          known he was her boyfriend I wouldn't have asked" [syn:
          {boyfriend}, {fellow}, {swain}, {young man}]
     2: a man who is much concerned with his dress and appearance
        [syn: {dandy}, {dude}, {fop}, {gallant}, {sheik}, {swell},
         {fashion plate}, {clotheshorse}]
     [also: {beaux} (pl)]
</WordDefinition>
    </Definition>
  </Definitions>
</WordDefinition>
