<?xml version="1.0" encoding="utf-8"?>
<WordDefinition xmlns:xsi="http://www.w3.org/2001/XMLSchema-instance" xmlns:xsd="http://www.w3.org/2001/XMLSchema" xmlns="http://services.aonaware.com/webservices/">
  <Word>gently</Word>
  <Definitions>
    <Definition>
      <Word>gently</Word>
      <Dictionary>
        <Id>gcide</Id>
        <Name>The Collaborative International Dictionary of English v.0.44</Name>
      </Dictionary>
      <WordDefinition>Gently \Gen"tly\, adv.
   In a gentle manner.
   [1913 Webster]

         My mistress gently chides the fault I made. --Dryden.
   [1913 Webster]
</WordDefinition>
    </Definition>
    <Definition>
      <Word>gently</Word>
      <Dictionary>
        <Id>wn</Id>
        <Name>WordNet (r) 2.0</Name>
      </Dictionary>
      <WordDefinition>gently
     adv 1: in a gradual manner; "a gently sloping terrain"
     2: in a gentle manner; "he talked gently to the injured animal"
        [syn: {mildly}]
     3: with little weight or force; "she kissed him lightly on the
        forehead" [syn: {lightly}, {softly}]
</WordDefinition>
    </Definition>
  </Definitions>
</WordDefinition>
