{"word":"arabia","results":[{"definition":"a peninsula between the Red Sea and the Persian Gulf; strategically important for its oil resources","partOfSpeech":"noun","synonyms":["arabian peninsula"],"regionOf":["ameer","emeer","emir","amir"],"instanceOf":["peninsula"],"hasMembers":["arabian","arab"],"hasParts":["katar peninsula","kingdom of saudi arabia","muscat and oman","najd","nejd","oman","qatar","qatar peninsula","republic of yemen","saudi arabia","sultanate of oman","united arab emirates","yemen","arabian desert","great arabian desert","hedjaz","hejaz","hijaz","katar"],"partOf":["asia"],"derivation":["arabian"]}],"syllables":{"count":4,"list":["a","ra","bi","a"]},"pronunciation":{"all":"ə'reɪbiə"},"frequency":3.43}
