{"word":"campaign","results":[{"definition":"several related operations aimed at achieving a particular goal (usually within geographical and temporal constraints)","partOfSpeech":"noun","synonyms":["military campaign"],"inCategory":["military machine","armed forces","armed services","military","war machine"],"typeOf":["military operation","operation"],"hasTypes":["expedition","military expedition","hostile expedition"],"hasInstances":["okinawa","petersburg","petersburg campaign","dardanelles campaign","dardanelles","wilderness campaign","okinawa campaign"]},{"definition":"go on a campaign; go off to war","partOfSpeech":"verb","synonyms":["take the field"],"entails":["war"],"hasTypes":["crusade"]},{"definition":"run, stand, or compete for an office or a position","partOfSpeech":"verb","synonyms":["run"],"typeOf":["run","race"],"hasTypes":["whistlestop","rerun","stump","cross-file","register"],"derivation":["campaigner"]},{"definition":"a race between candidates for elective office","partOfSpeech":"noun","synonyms":["political campaign","run"],"typeOf":["race"],"hasTypes":["senate campaign","governor's race","senate race","campaign for governor"],"examples":["I managed his campaign for governor"]},{"definition":"an overland journey by hunters (especially in Africa)","partOfSpeech":"noun","synonyms":["hunting expedition","safari"],"inRegion":["africa"],"typeOf":["expedition"]},{"definition":"exert oneself continuously, vigorously, or obtrusively to gain an end or engage in a crusade for a certain cause or person; be an advocate for","partOfSpeech":"verb","synonyms":["agitate","crusade","fight","press","push"],"typeOf":["advertize","advertise","promote","push"],"verbGroup":["promote","push","advertise","advertize"]},{"definition":"a series of actions advancing a principle or tending toward a particular end","partOfSpeech":"noun","synonyms":["cause","crusade","drive","effort","movement"],"typeOf":["venture"],"hasTypes":["consumerism","electioneering","feminism","feminist movement","fund-raising campaign","fund-raising drive","fund-raising effort","gay lib","gay liberation movement","ad blitz","ad campaign","advertising campaign","anti-war movement","campaigning","candidacy","candidature","charm campaign","lost cause","political campaign","reform","war","women's lib","women's liberation movement","youth crusade","youth movement"],"examples":["he supported populist campaigns"]}],"syllables":{"count":2,"list":["cam","paign"]},"pronunciation":{"all":"kæm'peɪn"},"frequency":4.23}
