{"word":"certainty","results":[{"definition":"something that is certain","partOfSpeech":"noun","synonyms":["foregone conclusion","sure thing"],"attribute":["certain","uncertain"],"typeOf":["quality"],"hasTypes":["unquestionableness","surety","unavoidability","unquestionability","predictability","cert","indisputability","indubitability","slam dunk","ineluctability","inevitability","inevitableness","moral certainty"],"antonyms":["uncertainty"],"examples":["his victory is a certainty"]},{"definition":"the state of being certain","partOfSpeech":"noun","attribute":["unsure","uncertain","incertain","sure","certain"],"typeOf":["cognitive state","state of mind"],"hasTypes":["self-assurance","authority","certitude","cocksureness","confidence","overconfidence","reliance","assurance","self-confidence","sureness","trust"],"antonyms":["uncertainty"],"examples":["his certainty reassured the others"]}],"syllables":{"count":3,"list":["cer","tain","ty"]},"pronunciation":{"all":"'sɜrtənti"},"frequency":3.67}
