{"word":"coloring","results":[{"definition":"a digestible substance used to give color to food","partOfSpeech":"noun","synonyms":["colouring","food color","food coloring","food colour","food colouring"],"typeOf":["food product","foodstuff"],"derivation":["color"]},{"definition":"the act or process of changing the color of something","partOfSpeech":"noun","synonyms":["colouring"],"typeOf":["change of color"],"hasTypes":["tinting","hair coloring","dyeing"],"derivation":["color"]},{"definition":"a visual attribute of things that results from the light they emit or transmit or reflect","partOfSpeech":"noun","synonyms":["color","colour","colouring"],"attribute":["colorful","coloured","colored","uncolored","uncoloured"],"typeOf":["visual property"],"hasTypes":["dithered colour","heather","heather mixture","mottle","nonsolid color","achromatic color","primary color","primary colour","shade","skin color","skin colour","spectral color","spectral colour","tincture","tint","tone","nonsolid colour","achromatic colour","chromatic color","chromatic colour","coloration","colouration","complexion","dithered color"],"derivation":["color"]}],"syllables":{"count":3,"list":["col","or","ing"]},"pronunciation":{"all":"'kələrɪŋ"},"frequency":3.03}
