{"word":"defined","results":[{"definition":"showing clearly the outline or profile or boundary","partOfSpeech":"adjective","synonyms":["outlined"],"similarTo":["distinct"],"examples":["hills defined against the evening sky"]},{"definition":"clearly characterized or delimited","partOfSpeech":"adjective","also":["definite"],"antonyms":["undefined"],"examples":["lost in a maze of words both defined and undefined","each child has clearly defined duties"]}],"syllables":{"count":2,"list":["de","fined"]},"pronunciation":"dɪ'faɪnd","frequency":3.52}
