{"word":"dissipation","results":[{"definition":"dissolute indulgence in sensual pleasure","partOfSpeech":"noun","synonyms":["dissolution","licentiousness","looseness","profligacy"],"typeOf":["intemperateness","intemperance","self-indulgence"],"derivation":["dissipate"]},{"definition":"useless or profitless activity; using or expending or consuming thoughtlessly or carelessly","partOfSpeech":"noun","synonyms":["waste","wastefulness"],"typeOf":["activity"],"hasTypes":["prodigality","squandering","waste of effort","waste of energy","waste of material","waste of money","waste of time","boondoggle","extravagance","high life","highlife","lavishness"],"derivation":["dissipate"],"examples":["mindless dissipation of natural resources"]},{"definition":"breaking up and scattering by dispersion","partOfSpeech":"noun","typeOf":["dispersion","scattering"],"derivation":["dissipate"],"examples":["the dissipation of the mist"]}],"syllables":{"count":4,"list":["dis","si","pa","tion"]},"pronunciation":{"all":",dɪsə'peɪʃən"},"frequency":1.97}
