{"word":"dolly","results":[{"definition":"a small replica of a person; used as a toy","partOfSpeech":"noun","synonyms":["doll"],"typeOf":["plaything","toy"],"hasTypes":["golliwog","golliwogg","kachina","paper doll","puppet","rag doll","sawdust doll","toy soldier"]},{"definition":"conveyance consisting of a wheeled platform for moving heavy objects","partOfSpeech":"noun","typeOf":["transport","conveyance"]},{"definition":"conveyance consisting of a wheeled support on which a camera can be mounted","partOfSpeech":"noun","typeOf":["transport","conveyance"]}],"syllables":{"count":2,"list":["dol","ly"]},"pronunciation":{"all":"'dɑli"},"frequency":3.88}
