{"word":"doll","results":[{"definition":"informal terms for a (young) woman","partOfSpeech":"noun","synonyms":["bird","chick","dame","skirt","wench"],"typeOf":["young woman","girl","miss","missy","young lady","fille"]},{"definition":"a small replica of a person; used as a toy","partOfSpeech":"noun","synonyms":["dolly"],"typeOf":["plaything","toy"],"hasTypes":["toy soldier","kachina","golliwog","golliwogg","paper doll","rag doll","puppet","sawdust doll"]}],"syllables":{"count":1,"list":["doll"]},"pronunciation":{"all":"dɑl"},"frequency":4.28}
