{"word":"domination","results":[{"definition":"power to dominate or defeat","partOfSpeech":"noun","synonyms":["mastery","supremacy"],"typeOf":["dominance","ascendancy","ascendence","ascendency","ascendance","control"],"hasTypes":["transcendency","superiority","transcendence"],"derivation":["dominate"]},{"definition":"social control by dominating","partOfSpeech":"noun","typeOf":["social control"],"hasTypes":["monopolization","subordination","bossism","mastery","monopolisation"],"derivation":["dominate"]}],"syllables":{"count":4,"list":["dom","i","na","tion"]},"pronunciation":{"all":",dɑmə'neɪʃən"},"frequency":3.42}
