{"word":"dry","results":[{"definition":"become dry or drier","partOfSpeech":"verb","synonyms":["dry out"],"typeOf":["change"],"hasTypes":["scorch","run dry","dry out"],"derivation":["drier"],"examples":["The laundry dries in the sun"]},{"definition":"a reformer who opposes the use of intoxicating beverages","partOfSpeech":"noun","synonyms":["prohibitionist"],"typeOf":["crusader","reformer","reformist","social reformer","meliorist"],"hasInstances":["carry amelia moore nation","carry nation","frances elizabeth caroline willard","nation","willard"]},{"definition":"lacking interest or stimulation; dull and lifeless","partOfSpeech":"adjective","synonyms":["juiceless"],"similarTo":["unstimulating","unexciting"],"examples":["a dry book","a dry lecture filled with trivial details"]},{"definition":"humorously sarcastic or mocking","partOfSpeech":"adjective","synonyms":["ironic","ironical","wry"],"similarTo":["humourous","humorous"],"derivation":["dryness"],"examples":["dry humor"]},{"definition":"remove the moisture from and make dry","partOfSpeech":"verb","synonyms":["dry out"],"cause":["dry out"],"typeOf":["modify","change","alter"],"hasTypes":["parch","rough-dry","blow-dry","sear","spin-dry","spray-dry","tumble dry","air","dehumidify","desiccate","drip-dry","dry up","exsiccate","dehydrate"],"antonyms":["wet"],"derivation":["drier"],"examples":["dry clothes","dry hair"]},{"definition":"practicing complete abstinence from alcoholic beverages","partOfSpeech":"adjective","synonyms":["teetotal"],"similarTo":["sober"],"derivation":["dryness"],"examples":["he's been dry for ten years"]},{"definition":"free from liquid or moisture; lacking natural or normal moisture or depleted of water; or no longer wet","partOfSpeech":"adjective","attribute":["wetness"],"similarTo":["sear","adust","air-dried","air-dry","arid","baked","bone-dry","bone dry","desiccated","dried","dried-out","dried-up","dry-shod","kiln-dried","parched","rainless","scorched","semi-dry","semiarid","sere","shriveled","shrivelled","sunbaked","thirsty","waterless","withered"],"antonyms":["wet"],"derivation":["dryness"],"examples":["dry land","dry clothes","a dry climate","dry splintery boards","a dry river bed","the paint is dry"]},{"definition":"having a large proportion of strong liquor","partOfSpeech":"adjective","similarTo":["alcoholic"],"examples":["a very dry martini is almost straight gin"]},{"definition":"having no adornment or coloration","partOfSpeech":"adjective","similarTo":["plain"],"examples":["dry facts","rattled off the facts in a dry mechanical manner"]},{"definition":"lacking warmth or emotional involvement","partOfSpeech":"adjective","similarTo":["unemotional"],"derivation":["dryness"],"examples":["a dry greeting","a dry reading of the lines","a dry critique"]},{"definition":"not producing milk","partOfSpeech":"adjective","similarTo":["milkless"],"antonyms":["wet"],"derivation":["dryness"],"examples":["a dry cow"]},{"definition":"not shedding tears","partOfSpeech":"adjective","similarTo":["tearless","dry-eyed"],"derivation":["dryness"],"examples":["dry sobs","with dry eyes"]},{"definition":"(of food) eaten without a spread or sauce or other garnish","partOfSpeech":"adjective","similarTo":["plain"],"examples":["dry toast","dry meat"]},{"definition":"(of liquor) having a low residual sugar content because of decomposition of sugar during fermentation","partOfSpeech":"adjective","also":["sour","nonsweet","sugarless"],"similarTo":["unsweet","sec","medium-dry","brut"],"antonyms":["sweet"],"examples":["a dry white burgundy","a dry Bordeaux"]},{"definition":"unproductive especially of the expected results","partOfSpeech":"adjective","similarTo":["unproductive"],"examples":["a dry run","a mind dry of new ideas"]},{"definition":"used of solid substances in contrast with liquid ones","partOfSpeech":"adjective","similarTo":["solid"],"examples":["dry weight"]},{"definition":"lacking moisture or volatile components","partOfSpeech":null,"antonyms":["wet"],"derivation":["dryness"],"examples":["dry paint"]},{"definition":"opposed to or prohibiting the production and sale of alcoholic beverages","partOfSpeech":null,"antonyms":["wet"],"examples":["the dry vote led by preachers and bootleggers","a dry state"]},{"definition":"without a mucous or watery discharge","partOfSpeech":null,"antonyms":["phlegmy"],"derivation":["dryness"],"examples":["a dry cough","that rare thing in the wintertime; a small child with a dry nose"]}],"syllables":{"count":1,"list":["dry"]},"pronunciation":{"all":"draɪ"},"frequency":4.63}
