{"word":"eddy","results":[{"definition":"flow in a circular current, of liquids","partOfSpeech":"verb","synonyms":["purl","swirl","whirl","whirlpool"],"typeOf":["course","run","feed","flow"]},{"definition":"a miniature whirlpool or whirlwind resulting when the current of a fluid doubles back on itself","partOfSpeech":"noun","synonyms":["twist"],"typeOf":["stream","current"]},{"definition":"founder of Christian Science in 1866 (1821-1910)","partOfSpeech":"noun","synonyms":["mary baker eddy","mary morse baker eddy"],"instanceOf":["religious person"]}],"syllables":{"count":2,"list":["ed","dy"]},"pronunciation":{"all":"'ɛdi"},"frequency":3.45}
