{"word":"exasperation","results":[{"definition":"an exasperated feeling of annoyance","partOfSpeech":"noun","synonyms":["aggravation"],"typeOf":["annoyance","vexation","chafe"],"derivation":["exasperate"]},{"definition":"actions that cause great irritation (or even anger)","partOfSpeech":"noun","typeOf":["irritation","annoyance","annoying","vexation"],"hasTypes":["exacerbation"],"derivation":["exasperate"]}],"syllables":{"count":5,"list":["ex","as","per","a","tion"]},"pronunciation":{"all":"ɪɡ,zæspə'reɪʃən"},"frequency":2.12}
