{"word":"grammatical","results":[{"definition":"of or pertaining to grammar","partOfSpeech":"adjective","synonyms":["grammatic"],"pertainsTo":["grammar"],"derivation":["grammar"],"examples":["grammatical rules","grammatical gender"]},{"definition":"conforming to the rules of grammar or usage accepted by native speakers","partOfSpeech":"adjective","synonyms":["well-formed"],"antonyms":["ungrammatical"],"derivation":["grammar"],"examples":["spoke in grammatical sentences"]}],"syllables":{"count":4,"list":["gram","mat","i","cal"]},"pronunciation":{"all":"grə'mætɪkəl"},"frequency":2.2}
