{"word":"hangover","results":[{"definition":"disagreeable aftereffects from the use of drugs (especially alcohol)","partOfSpeech":"noun","synonyms":["katzenjammer"],"typeOf":["discomfort","uncomfortableness"]},{"definition":"an official who remains in office after his term","partOfSpeech":"noun","synonyms":["holdover"],"typeOf":["functionary","official"]},{"definition":"something that has survived from the past","partOfSpeech":"noun","synonyms":["holdover"],"typeOf":["survival"],"examples":["hangovers from the 19th century"]}],"syllables":{"count":3,"list":["hang","o","ver"]},"pronunciation":{"all":"'hæŋ,oʊvər"},"frequency":3.52}
