{"word":"innocent","results":[{"definition":"not knowledgeable about something specified","partOfSpeech":"adjective","synonyms":["unacquainted"],"similarTo":["uninformed"],"examples":["American tourists wholly innocent of French"]},{"definition":"lacking in sophistication or worldliness","partOfSpeech":"adjective","synonyms":["ingenuous"],"similarTo":["naive","naif"],"derivation":["innocence"],"examples":["a child's innocent stare"]},{"definition":"completely wanting or lacking","partOfSpeech":"adjective","synonyms":["barren","destitute","devoid","free"],"similarTo":["nonexistent"],"examples":["innocent of literary merit"]},{"definition":"a person who lacks knowledge of evil","partOfSpeech":"noun","synonyms":["inexperienced person"],"typeOf":["person","somebody","someone","mortal","individual","soul"],"hasTypes":["boy scout","lamb","naif","virgin","dear"]},{"definition":"free from evil or guilt","partOfSpeech":"adjective","synonyms":["clean-handed","guiltless"],"also":["exculpatory","righteous"],"similarTo":["not guilty","vindicated","absolved","acquitted","blameless","clear","cleared","exculpated","exonerated","unimpeachable","inculpable","irreproachable"],"antonyms":["guilty"],"derivation":["innocence"],"examples":["an innocent child","the principle that one is innocent until proved guilty"]},{"definition":"free from sin","partOfSpeech":"adjective","synonyms":["impeccant","sinless"],"similarTo":["virtuous"],"derivation":["innocence"]},{"definition":"lacking intent or capacity to injure","partOfSpeech":"adjective","synonyms":["innocuous"],"similarTo":["harmless"],"examples":["an innocent prank"]},{"definition":"(used of things) lacking sense or awareness","partOfSpeech":"adjective","usageOf":["archaism","archaicism"],"similarTo":["unconscious"],"examples":["fine innocent weather"]}],"syllables":{"count":3,"list":["in","no","cent"]},"pronunciation":{"all":"'ɪnəsənt"},"frequency":4.68}
