{"word":"john","results":[{"definition":"a room or building equipped with one or more toilets","partOfSpeech":"noun","synonyms":["bathroom","can","lav","lavatory","privy","toilet"],"typeOf":["room"],"hasTypes":["comfort station","convenience","public lavatory","restroom","closet","washroom","water closet","wash room","w.c.","head","toilet facility","loo","public convenience","public toilet"],"hasParts":["toilet","commode","potty","crapper","throne","stool","can","pot"]},{"definition":"youngest son of Henry II; King of England from 1199 to 1216; succeeded to the throne on the death of his brother Richard I; lost his French possessions; in 1215 John was compelled by the barons to sign the Magna Carta (1167-1216)","partOfSpeech":"noun","synonyms":["john lackland","king john"],"instanceOf":["king of england","king of great britain"],"memberOf":["plantagenet","plantagenet line"]},{"definition":"a prostitute's customer","partOfSpeech":"noun","synonyms":["trick","whoremaster","whoremonger"],"typeOf":["client","customer"]},{"definition":"(New Testament) disciple of Jesus; traditionally said to be the author of the 4th Gospel and three epistles and the book of Revelation","partOfSpeech":"noun","synonyms":["john the divine","john the evangelist","saint john","saint john the apostle","st. john","st. john the apostle"],"inCategory":["new testament"],"instanceOf":["apostle","evangelist","saint"]},{"definition":"the last of the four Gospels in the New Testament","partOfSpeech":"noun","synonyms":["gospel according to john"],"instanceOf":["gospels","gospel","evangel","book"],"partOf":["new testament"]}],"syllables":{"count":1,"list":["john"]},"pronunciation":{"all":"dʒɑn"},"frequency":5.14}
