{"word":"locate","results":[{"definition":"assign a location to","partOfSpeech":"verb","synonyms":["place","site"],"typeOf":["place","station","send","post"],"derivation":["location"],"examples":["The company located some of their agents in Los Angeles"]},{"definition":"discover the location of; determine the place of; find by searching or examining","partOfSpeech":"verb","synonyms":["turn up"],"typeOf":["find","regain"],"hasTypes":["nail","pinpoint","unearth"],"verbGroup":["excavate","turn up","dig up"],"derivation":["location"],"examples":["Can you locate your cousins in the Midwest?"]},{"definition":"determine or indicate the place, site, or limits of, as if by an instrument or by a survey","partOfSpeech":"verb","synonyms":["situate"],"typeOf":["find out","find","ascertain","determine"],"hasTypes":["acquire","base","localise","localize","map","place","radiolocate"],"derivation":["locater","location","locator"],"examples":["Our sense of sight enables us to locate objects in space"]},{"definition":"take up residence and become established","partOfSpeech":"verb","synonyms":["settle"],"entails":["move"],"hasTypes":["resettle","colonize","colonise"],"derivation":["location"]}],"syllables":{"count":2,"list":["lo","cate"]},"pronunciation":{"all":"'loʊkeɪt"},"frequency":3.83}
