{"word":"lowly","results":[{"definition":"of low birth or station (`base' is archaic in this sense)","partOfSpeech":"adjective","synonyms":["base","baseborn","humble"],"similarTo":["lowborn"],"examples":["of humble (or lowly) birth"]},{"definition":"low or inferior in station or quality","partOfSpeech":"adjective","synonyms":["humble","low","modest","small"],"similarTo":["inferior"],"examples":["a lowly parish priest"]},{"definition":"used of unskilled work (especially domestic work)","partOfSpeech":"adjective","synonyms":["humble","menial"],"similarTo":["unskilled"]},{"definition":"inferior in rank or status","partOfSpeech":"adjective","synonyms":["junior-grade","lower-ranking","petty","secondary","subaltern"],"similarTo":["junior"],"examples":["a lowly corporal"]}],"syllables":{"count":2,"list":["low","ly"]},"pronunciation":{"all":"'loʊli"},"frequency":3.34}
