{"word":"minor","results":[{"definition":"not of legal age","partOfSpeech":"adjective","synonyms":["nonaged","underage"],"inCategory":["jurisprudence","law"],"antonyms":["major"],"derivation":["minority"],"examples":["minor children"]},{"definition":"relatively moderate, limited, or small","partOfSpeech":"adjective","synonyms":["modest","pocket-size","pocket-sized","small","small-scale"],"similarTo":["limited"]},{"definition":"a young person of either sex","partOfSpeech":"noun","synonyms":["child","fry","kid","nestling","nipper","shaver","small fry","tiddler","tike","tyke","youngster"],"typeOf":["juvenile","juvenile person"],"hasTypes":["buster","changeling","child prodigy","yearling","foster-child","foster child","fosterling","wonder child","imp","infant prodigy","bairn","urchin","tot","sprog","street child","toddler","kiddie","kiddy","kindergartener","kindergartner","bambino","monkey","waif","orphan","peanut","picaninny","piccaninny","pickaninny","poster child","preschooler","rapscallion","rascal","scalawag","scallywag","scamp","silly"],"hasParts":["child's body"]},{"definition":"warranting only temporal punishment","partOfSpeech":"adjective","synonyms":["venial"],"inCategory":["divinity","theology"],"similarTo":["pardonable"]},{"definition":"have as one's secondary field of study","partOfSpeech":"verb","typeOf":["study"],"examples":["in collee she minored in mathematics"]},{"definition":"inferior in number or size or amount","partOfSpeech":"adjective","attribute":["minority"],"antonyms":["major"],"derivation":["minority"],"examples":["a minor share of the profits"]},{"definition":"(of a scale or mode) having half steps between the second and third degrees, and (usually) the fifth and sixth degrees, and the seventh and eighth degrees","partOfSpeech":"adjective","inCategory":["music"],"antonyms":["major"],"examples":["the minor keys","in B flat minor"]},{"definition":"of lesser importance or stature or rank","partOfSpeech":"adjective","similarTo":["secondary","peanut","insignificant"],"antonyms":["major"],"examples":["a minor poet","had a minor part in the play","a minor official","many of these hardy adventurers were minor noblemen","minor back roads"]},{"definition":"of the younger of two boys with the same family name","partOfSpeech":"adjective","inRegion":["great britain","britain","u.k.","uk","united kingdom","united kingdom of great britain and northern ireland"],"similarTo":["junior"],"examples":["Jones minor"]},{"definition":"lesser in scope or effect","partOfSpeech":null,"antonyms":["major"],"examples":["had minor differences","a minor disturbance"]},{"definition":"of lesser seriousness or danger","partOfSpeech":null,"antonyms":["major"],"examples":["suffered only minor injuries","some minor flooding","a minor tropical disturbance"]},{"definition":"of your secondary field of academic concentration or specialization","partOfSpeech":null,"antonyms":["major"]}],"syllables":{"count":2,"list":["mi","nor"]},"pronunciation":{"all":"'maɪnər"},"frequency":4.13}
