{"word":"muster","results":[{"definition":"compulsory military service","partOfSpeech":"noun","synonyms":["conscription","draft","selective service"],"inCategory":["military","armed forces","military machine","war machine","armed services"],"typeOf":["mobilisation","mobilization","militarization","militarisation"],"hasTypes":["levy","levy en masse"]},{"definition":"gather or bring together","partOfSpeech":"verb","synonyms":["come up","muster up","rally","summon"],"typeOf":["pull together","garner","gather","collect"],"examples":["muster the courage to do something"]},{"definition":"a gathering of military personnel for duty","partOfSpeech":"noun","inCategory":["armed forces","armed services","military","military machine","war machine"],"typeOf":["gathering","assemblage"],"examples":["he was thrown in the brig for missing muster"]},{"definition":"call to duty, military service, jury duty, etc.","partOfSpeech":"verb","typeOf":["call","send for"]}],"syllables":{"count":2,"list":["mus","ter"]},"pronunciation":{"all":"'mustɜr"},"frequency":3.09}
