{"word":"nod","results":[{"definition":"a sign of assent or salutation or command","partOfSpeech":"noun","typeOf":["motion","gesture"]},{"definition":"be almost asleep","partOfSpeech":"verb","typeOf":["drowse"],"examples":["The old man sat nodding by the fireplace"]},{"definition":"express or signify by nodding","partOfSpeech":"verb","typeOf":["gesture","motion","gesticulate"],"examples":["He nodded his approval"]},{"definition":"lower and raise the head, as to indicate assent or agreement or confirmation","partOfSpeech":"verb","typeOf":["communicate","intercommunicate"],"examples":["The teacher nodded when the student gave the right answer"]},{"definition":"sway gently back and forth, as in a nodding motion","partOfSpeech":"verb","typeOf":["move"],"examples":["the flowers were nodding in the breeze"]},{"definition":"the act of nodding the head","partOfSpeech":"noun","typeOf":["inclination","inclining"],"hasTypes":["nutation"]},{"definition":"let the head fall forward through drowsiness","partOfSpeech":null,"examples":["The old man was nodding in his chair"]}],"syllables":{"count":1,"list":["nod"]},"pronunciation":{"all":"nɑd"},"frequency":3.57}
