{"word":"orbit","results":[{"definition":"the (usually elliptical) path described by one celestial body in its revolution about another","partOfSpeech":"noun","synonyms":["celestial orbit"],"typeOf":["route","path","itinerary"],"hasTypes":["geosynchronous orbit"],"hasParts":["apoapsis","point of apoapsis","periapsis","point of periapsis"],"derivation":["orbital"],"examples":["he plotted the orbit of the moon"]},{"definition":"an area in which something acts or operates or has power or control:","partOfSpeech":"noun","synonyms":["ambit","compass","range","reach","scope"],"typeOf":["extent"],"hasTypes":["sweep","purview","spectrum","confines","contrast","latitude","palette","approximate range","expanse","view","internationality","ballpark","gamut","pallet","horizon","internationalism"],"examples":["in the political orbit of a world power"]},{"definition":"a particular environment or walk of life","partOfSpeech":"noun","synonyms":["area","arena","domain","field","sphere"],"typeOf":["environment"],"hasTypes":["province","political arena","political sphere","distaff","front","kingdom","land","lap","realm","preserve","responsibility"],"examples":["he's out of my orbit"]},{"definition":"move in an orbit","partOfSpeech":"verb","synonyms":["orb","revolve"],"typeOf":["circle"],"hasTypes":["retrograde"],"derivation":["orbiter"],"examples":["The moon orbits around the Earth","The planets are orbiting the sun","electrons orbit the nucleus"]},{"definition":"the bony cavity in the skull containing the eyeball","partOfSpeech":"noun","synonyms":["cranial orbit","eye socket","orbital cavity"],"typeOf":["cavum","bodily cavity","cavity"],"hasParts":["lacrimal bone"],"partOf":["skull"],"derivation":["orbital"]},{"definition":"the path of an electron around the nucleus of an atom","partOfSpeech":"noun","synonyms":["electron orbit"],"typeOf":["path","itinerary","route"],"derivation":["orbital"]}],"syllables":{"count":2,"list":["or","bit"]},"pronunciation":{"all":"'ɔrbɪt"},"frequency":3.71}
