{"word":"outburst","results":[{"definition":"a sudden violent disturbance","partOfSpeech":"noun","synonyms":["tumultuous disturbance"],"typeOf":["disturbance"]},{"definition":"a sudden intense happening","partOfSpeech":"noun","synonyms":["burst","flare-up"],"typeOf":["happening","occurrence","occurrent","natural event"],"hasTypes":["rush","salvo"],"examples":["an outburst of heavy rain"]},{"definition":"an unrestrained expression of emotion","partOfSpeech":"noun","synonyms":["blowup","ebullition","effusion","gush"],"typeOf":["expression","reflexion","reflection","manifestation"],"hasTypes":["acting out","cry","explosion","flare"]}],"syllables":{"count":2,"list":["out","burst"]},"pronunciation":{"all":"'aʊtbɜrst"},"frequency":2.95}
