{"word":"overlook","results":[{"definition":"look down on","partOfSpeech":"verb","synonyms":["command","dominate","overtop"],"typeOf":["lie"],"hasTypes":["dwarf","overshadow","shadow"]},{"definition":"be oriented in a certain direction","partOfSpeech":"verb","synonyms":["look across","look out on","look out over"],"typeOf":["lie"],"examples":["The apartment overlooks the Hudson"]},{"definition":"leave undone or leave out","partOfSpeech":"verb","synonyms":["drop","leave out","miss","neglect","omit","overleap","pretermit"],"hasTypes":["skip","skip over","forget","jump","pass over"]},{"definition":"a high place affording a good view","partOfSpeech":"noun","typeOf":["topographic point","spot","place"]},{"definition":"look past, fail to notice","partOfSpeech":"verb","typeOf":["lose","miss"]},{"definition":"watch over","partOfSpeech":"verb","typeOf":["survey"],"examples":["I am overlooking her work"]}],"syllables":{"count":3,"list":["o","ver","look"]},"pronunciation":{"all":",oʊvər'lʊk","noun":"'oʊvər,lʊk","verb":",oʊvər'lʊk"},"frequency":3.3}
