{"word":"port","results":[{"definition":"(computer science) computer circuit consisting of the hardware and associated circuitry that links one device with another (especially a computer and a hard disk drive or other peripherals)","partOfSpeech":"noun","synonyms":["interface"],"inCategory":["computing","computer science"],"typeOf":["computer circuit"],"hasTypes":["small computer system interface","parallel port","scsi","parallel interface","serial port"]},{"definition":"sweet dark-red dessert wine originally from Portugal","partOfSpeech":"noun","synonyms":["port wine"],"typeOf":["fortified wine"]},{"definition":"the left side of a ship or aircraft to someone who is aboard and facing the bow or nose","partOfSpeech":"noun","synonyms":["larboard"],"typeOf":["side"]},{"definition":"located on the left side of a ship or aircraft","partOfSpeech":"adjective","synonyms":["larboard"],"similarTo":["left"]},{"definition":"an opening (in a wall or ship or armored vehicle) for firing through","partOfSpeech":"noun","synonyms":["embrasure","porthole"],"inCategory":["ship"],"typeOf":["opening"]},{"definition":"a place (seaport or airport) where people and merchandise can enter or leave a country","partOfSpeech":"noun","typeOf":["geographical point","geographic point"],"hasTypes":["haven","outport","free port","home port","harbor","seaport","port of entry","point of entry","entrepot","treaty port","transshipment center","harbour"],"hasInstances":["alexandria","algerian capital","algiers","alpena","angolan capital","annaba","antalya","antofagasta","antwerp","antwerpen","anvers","arhus","aspinwall","asuncion","auckland","ayr","bahia blanca","baku","baltimore","bangkok","banjul","barcelona","barranquilla","basia","basra","beira","belem","benghazi","bergen","bida","bordeaux","bremerhaven","brest","bridgeport","bridgetown","brindisi","bristol","buenos aires","cadiz","cairo","calais","cannes","canton","cape town","capital of argentina","capital of azerbaijan","capital of barbados","capital of djibouti","capital of egypt","capital of estonia","capital of finland","capital of gambia","capital of guinea","capital of hawaii","capital of iceland","capital of ireland","capital of latvia","capital of liberia","capital of norway","capital of oman","capital of paraguay","capital of portugal","capital of qatar","capital of senegal","capital of seychelles","capital of sierra leone","capital of somalia","capital of suriname","capital of tanzania","capital of thailand","capital of tunisia","cartagena","casablanca","castries","charleston","chemulpo","cherbourg","chicago","chittagong","christiania","ciudad bolivar","colon","conakry","corinth","cork","cotonou","cumana","dairen","dakar","dalian","danzig","dar es salaam","detroit","djibouti","dneprodzerzhinsk","doha","dubai","dublin","dubrovnik","duluth","dunkerque","dunkirk","durazzo","durban","durres","egyptian capital","el beda","el iskandriyah","el qahira","feliz lusitania","finnish capital","freetown","galway","gand","gateway to the west","gdansk","gent","georgetown","ghent","glasgow","goeteborg","goteborg","gothenburg","guangzhou","haifa","haiphong","hamburg","hamilton","hannover","hanover","hawaiian capital","hefa","helsingfors","helsinki","hiroshima","hobart","hodeida","hong kong","honolulu","houston","hull","incheon","inchon","irish capital","izmir","jaffa","jed'dah","jeddah","jidda","jiddah","joppa","kingston-upon hull","kisumu","kobe","konakri","korinthos","krung thep","kuangchou","kwangchow","la spezia","lagos","latakia","le havre","liberian capital","limerick","lisboa","lisbon","liverpool","lobito","luanda","lushun","maarianhamina","malaga","malmo","maracaibo","mariehamn","marseille","marseilles","masqat","massawa","mawlamyine","mazatlan","messina","mobile","mogadiscio","mogadishu","mombasa","monrovia","montego bay","motor city","motown","moulmein","mukalla","murmansk","muscat","nagasaki","nantes","naples","napoli","natal","newcastle","newcastle-upon-tyne","newport","newport news","nidaros","norfolk","oakland","odesa","odessa","oporto","oran","osaka","oslo","pago pago","palermo","pango pango","para","paramaribo","patrai","patras","pernambuco","ragusa","aarhus","abadan","acapulco","acapulco de juarez","accho","acre","adalia","aden","akka","akko","al-hudaydah","al-mukalla","al ladhiqiyah","al qahira","alborg","swansea","talien","tallin","tallinn","tampico","tanga","tarabulus","tarabulus ash-sham","thessalonica","thessaloniki","thunder bay","toulon","trablous","tripoli","trondheim","tunis","tyre","valdez","valparaiso","vancouver","varna","veracruz","victoria","waterford","windy city","yafo","yokohama","pompey","port arthur","port louis","port sudan","porto","portsmouth","pusan","aalborg","recife","reykjavik","riga","rostov","rostov na donu","rostov on don","saint john","saint john's","saint louis","salonica","salonika","samarang","santa maria de belem","santiago","santiago de cuba","santos","savannah","semarang","setubal","sevilla","seville","shanghai","smyrna","sousse","st. john","st. john's","st. louis","st. mary of bethlehem","stabroek","stavanger","sunderland","sur","susa","susah"]},{"definition":"bring to port","partOfSpeech":"verb","examples":["the captain ported the ship at night"]},{"definition":"carry, bear, convey, or bring","partOfSpeech":"verb","typeOf":["carry","transport"],"derivation":["porter","portage"],"examples":["The small canoe could be ported easily"]},{"definition":"carry or hold with both hands diagonally across the body, especially of weapons","partOfSpeech":"verb","typeOf":["transport","carry"],"examples":["port a rifle"]},{"definition":"drink port","partOfSpeech":"verb","typeOf":["fuddle","hit the bottle","booze","drink"],"examples":["We were porting all in the club after dinner"]},{"definition":"land at or reach a port","partOfSpeech":"verb","typeOf":["land","set down"],"examples":["The ship finally ported"]},{"definition":"modify (software) for use on a different machine or platform","partOfSpeech":"verb","typeOf":["modify","alter","change"]},{"definition":"put or turn on the left side, of a ship","partOfSpeech":"verb","typeOf":["turn"],"examples":["port the helm"]},{"definition":"turn or go to the port or left side, of a ship","partOfSpeech":"verb","typeOf":["turn"],"examples":["The big ship was slowly porting"]}],"syllables":{"count":1,"list":["port"]},"pronunciation":{"all":"poʊrt"},"frequency":4.16}
