{"word":"probation","results":[{"definition":"a trial period during which an offender has time to redeem himself or herself","partOfSpeech":"noun","typeOf":["test period","trial period"],"derivation":["probate","probationary"]},{"definition":"a trial period during which your character and abilities are tested to see whether you are suitable for work or for membership","partOfSpeech":"noun","typeOf":["trial period","test period"],"derivation":["probationary"]},{"definition":"(law) a way of dealing with offenders without imprisoning them; a defendant found guilty of a crime is released by the court without imprisonment subject to conditions imposed by the court","partOfSpeech":"noun","inCategory":["jurisprudence","law"],"typeOf":["release","liberation","freeing"],"derivation":["probate"],"examples":["probation is part of the sentencing process"]}],"syllables":{"count":3,"list":["pro","ba","tion"]},"pronunciation":{"all":"proʊ'beɪʃən"},"frequency":3.71}
