{"word":"protagonist","results":[{"definition":"a person who backs a politician or a team etc.","partOfSpeech":"noun","synonyms":["admirer","booster","champion","friend","supporter"],"typeOf":["proponent","advocator","advocate","exponent"],"hasTypes":["boswell","cheerleader","confederate","corporatist","endorser","enthusiast","whig","anglophil","anglophile","believer","verifier","voucher","wassailer","well-wisher","francophil","francophile","free trader","functionalist","graecophile","indorser","jacobite","loyalist","mainstay","maintainer","new dealer","partisan","partizan","philhellene","philhellenist","pillar","ratifier","roundhead","seconder","shavian","stalwart","subscriber","sustainer","sympathiser","sympathizer","toaster","truster","upholder"]},{"definition":"the principal character in a work of fiction","partOfSpeech":"noun","synonyms":["agonist"],"typeOf":["fictional character","fictitious character","character"],"hasTypes":["antihero"]}],"syllables":{"count":4,"list":["pro","tag","o","nist"]},"pronunciation":{"all":"proʊ'tæɡənɪst"},"frequency":2.87}
