{"word":"reborn","results":[{"definition":"spiritually reborn or converted","partOfSpeech":"adjective","synonyms":["born-again"],"similarTo":["regenerate"]},{"definition":"restored to new life and vigor","partOfSpeech":"adjective","synonyms":["revitalised","revitalized"],"similarTo":["revived"],"examples":["Berlin has been reborn after probably the most intense period of construction since the post-war period."]}],"syllables":{"count":2,"list":["re","born"]},"pronunciation":{"all":"ri'bɔrn"},"frequency":3.65}
