{"word":"self-conscious","results":[{"definition":"aware of yourself as an individual or of your own being and actions and thoughts","partOfSpeech":"adjective","synonyms":["self-aware"],"similarTo":["conscious"],"derivation":["self-consciousness"],"examples":["self-conscious awareness","self-conscious about their roles as guardians of the social values"]},{"definition":"excessively and uncomfortably conscious of your appearance or behavior","partOfSpeech":"adjective","similarTo":["uncomfortable"],"derivation":["self-consciousness"],"examples":["self-conscious teenagers","wondered if she could ever be untidy without feeling self-conscious about it"]}],"syllables":{"count":2,"list":["self-con","scious"]},"pronunciation":{"all":"sɛlf_'kɑnʃəs"}}
