{"word":"smashed","results":[{"definition":"very drunk","partOfSpeech":"adjective","synonyms":["besotted","blind drunk","blotto","cockeyed","crocked","fuddled","loaded","pie-eyed","pissed","pixilated","plastered","slopped","sloshed","soaked","soused","sozzled","squiffy","stiff","tight","wet"],"usageOf":["argot","cant","jargon","lingo","patois","slang","vernacular"],"similarTo":["drunk","gone","inebriated","intoxicated","ripped"]}],"syllables":{"count":1,"list":["smashed"]},"pronunciation":{"all":"smæʃt"},"frequency":3.92}
