{"word":"sprinkling","results":[{"definition":"a light shower that falls in some locations and not others nearby","partOfSpeech":"noun","synonyms":["scattering","sprinkle"],"typeOf":["rain shower","shower"],"derivation":["sprinkle"]},{"definition":"a small number (of something) dispersed haphazardly","partOfSpeech":"noun","synonyms":["scattering"],"typeOf":["small indefinite amount","small indefinite quantity"],"derivation":["sprinkle"],"examples":["a sprinkling of grey at his temples"]},{"definition":"the act of sprinkling water in baptism (rare)","partOfSpeech":"noun","synonyms":["aspersion"],"typeOf":["baptism"]},{"definition":"the act of sprinkling or splashing water","partOfSpeech":"noun","synonyms":["sparge","sprinkle"],"typeOf":["watering"],"derivation":["sprinkle"],"examples":["baptized with a sprinkling of holy water"]}],"syllables":{"count":2,"list":["sprin","kling"]},"pronunciation":{"all":"'sprɪŋklɪŋ"},"frequency":2.57}
