{"word":"stretch","results":[{"definition":"exercise designed to extend the limbs and muscles to their full extent","partOfSpeech":"noun","synonyms":["stretching"],"typeOf":["workout","exercising","physical exertion","exercise","physical exercise"],"hasTypes":["pandiculation"]},{"definition":"occupy a large, elongated area","partOfSpeech":"verb","synonyms":["stretch along"],"typeOf":["be"],"examples":["The park stretched beneath the train line"]},{"definition":"corrupt, debase, or make impure by adding a foreign or inferior substance; often by replacing valuable ingredients with inferior ones","partOfSpeech":"verb","synonyms":["adulterate","debase","dilute","load"],"typeOf":["corrupt","spoil"],"hasTypes":["doctor","water down","sophisticate","doctor up"],"verbGroup":["extend"]},{"definition":"lie down comfortably","partOfSpeech":"verb","synonyms":["stretch out"],"typeOf":["lie down","lie"],"examples":["To enjoy the picnic, we stretched out on the grass"]},{"definition":"the act of physically reaching or thrusting out","partOfSpeech":"noun","synonyms":["reach","reaching"],"typeOf":["motion","move","motility","movement"],"hasTypes":["outreach"]},{"definition":"extend or stretch out to a greater or the full length","partOfSpeech":"verb","synonyms":["extend","stretch out","unfold"],"typeOf":["deform","change form","change shape"],"verbGroup":["extend"],"examples":["stretch out that piece of cloth"]},{"definition":"increase in quantity or bulk by adding a cheaper substance","partOfSpeech":"verb","synonyms":["extend"],"typeOf":["increase"],"verbGroup":["debase","adulterate","dilute","load"],"examples":["stretch the soup by adding some more cream"]},{"definition":"make long or longer by pulling and stretching","partOfSpeech":"verb","synonyms":["elongate"],"typeOf":["lengthen"],"hasTypes":["tree","shoetree"],"derivation":["stretching","stretcher"],"examples":["stretch the fabric"]},{"definition":"an unbroken period of time during which you do something","partOfSpeech":"noun","synonyms":["stint"],"typeOf":["duration","continuance"],"examples":["there were stretches of boredom","he did a stretch in the federal penitentiary"]},{"definition":"the capacity for being stretched","partOfSpeech":"noun","synonyms":["stretchability","stretchiness"],"typeOf":["elasticity","snap"],"derivation":["stretchy"]},{"definition":"extend one's body or limbs","partOfSpeech":"verb","synonyms":["stretch out"],"typeOf":["move"],"examples":["Let's stretch for a minute--we've been sitting here for over 3 hours"]},{"definition":"extend one's limbs or muscles, or the entire body","partOfSpeech":"verb","synonyms":["extend"],"typeOf":["tense up","tense","strain"],"hasTypes":["crane","spread-eagle","stretch out"],"derivation":["stretching"]},{"definition":"a large and unbroken expanse or distance","partOfSpeech":"noun","typeOf":["expanse"],"hasTypes":["slack water","slack"],"examples":["a stretch of highway","a stretch of clear water"]},{"definition":"a straightaway section of a racetrack","partOfSpeech":"noun","inCategory":["racing"],"typeOf":["straight","straightaway"],"hasTypes":["homestretch"],"partOf":["racetrack","track","racecourse","raceway"]},{"definition":"become longer by being stretched and pulled","partOfSpeech":"verb","typeOf":["grow"],"hasTypes":["yield","give"],"antonyms":["shrink"],"examples":["The fabric stretches"]},{"definition":"easily stretched","partOfSpeech":"adjective","similarTo":["elastic"],"examples":["stretch hosiery"]},{"definition":"extend the scope or meaning of; often unduly","partOfSpeech":"verb","typeOf":["broaden","extend","widen"],"examples":["stretch my patience","stretch the imagination"]},{"definition":"extension to or beyond the ordinary limit","partOfSpeech":"noun","typeOf":["extension"],"examples":["running at full stretch","by no stretch of the imagination","beyond any stretch of his understanding"]},{"definition":"having an elongated seating area","partOfSpeech":"adjective","similarTo":["long"],"examples":["a stretch limousine"]},{"definition":"pull in opposite directions","partOfSpeech":"verb","typeOf":["pull","draw"],"hasTypes":["draw","pull back"],"examples":["During the Inquisition, the torturers would stretch their victims on a rack"]}],"syllables":{"count":1,"list":["stretch"]},"pronunciation":{"all":"strɛʧ"},"frequency":4.12}
