{"word":"supernatural","results":[{"definition":"supernatural forces and events and beings collectively","partOfSpeech":"noun","synonyms":["occult"],"typeOf":["cause","causal agency","causal agent"],"hasMembers":["spiritual being","supernatural being"],"hasParts":["theurgy","destiny","fate"],"examples":["She doesn't believe in the supernatural"]},{"definition":"not existing in nature or subject to explanation according to natural laws; not physical or material","partOfSpeech":"adjective","also":["unreal"],"similarTo":["wizardly","transcendental","transmundane","uncanny","unearthly","weird","witching","witchlike","wizard","apparitional","charming","eerie","eldritch","elfin","fey","ghostlike","ghostly","magic","magical","marvellous","marvelous","metaphysical","miraculous","necromantic","nonnatural","otherworldly","phantasmal","preternatural","sorcerous","spectral","spiritual","talismanic"],"antonyms":["natural"],"derivation":["supernaturalness"],"examples":["supernatural forces and occurrences and beings"]}],"syllables":{"count":5,"list":["su","per","nat","u","ral"]},"pronunciation":{"all":",supər'næʧərəl"},"frequency":3.6}
