{"word":"tolerable","results":[{"definition":"about average; acceptable","partOfSpeech":"adjective","synonyms":["adequate","fair to middling","passable"],"similarTo":["satisfactory"]},{"definition":"capable of being borne or endured","partOfSpeech":"adjective","also":["permissible","allowable"],"similarTo":["resistant","sufferable","supportable","tolerant","bearable","endurable"],"antonyms":["intolerable"],"examples":["the climate is at least tolerable"]}],"syllables":{"count":4,"list":["tol","er","a","ble"]},"pronunciation":{"all":"'tɑlərəbəl"},"frequency":2.62}
