{"word":"treatment","results":[{"definition":"the management of someone or something","partOfSpeech":"noun","synonyms":["handling"],"typeOf":["management","direction"],"hasTypes":["dealing","bioremediation"],"derivation":["treat"],"examples":["the treatment of water sewage","the right to equal treatment in the criminal justice system"]},{"definition":"an extended communication (often interactive) dealing with some particular topic","partOfSpeech":"noun","synonyms":["discourse","discussion"],"typeOf":["communication","communicating"],"hasTypes":["enlargement","elaboration","talk","expansion","detail","dilation","consideration"],"derivation":["treat"],"examples":["his treatment of the race question is badly biased"]},{"definition":"care provided to improve a situation (especially medical procedures or applications that are intended to relieve illness or injury)","partOfSpeech":"noun","synonyms":["intervention"],"typeOf":["care","tending","attention","aid"],"hasTypes":["orthodontic treatment","acupuncture","autogenic therapy","autogenic training","autogenics","chiropractic","detoxification","naturopathy","acupressure","orthoptics","osteoclasis","osteopathy","rest-cure","shiatsu","stylostixis","fomentation","g-jo","hydropathy","hydrotherapy","massage","medical aid","medical care","modality","naprapathy"],"hasParts":["remedy","cure","curative","therapeutic"],"derivation":["treat"]},{"definition":"a manner of dealing with something artistically","partOfSpeech":"noun","typeOf":["artistic style","idiom"],"examples":["his treatment of space borrows from Italian architecture"]}],"syllables":{"count":2,"list":["treat","ment"]},"pronunciation":{"all":"'tritmənt"},"frequency":4.46}
