{"word":"treasury","results":[{"definition":"negotiable debt obligations of the United States government which guarantees that interest and principal payments will be paid on time","partOfSpeech":"noun","synonyms":["treasury obligations"],"typeOf":["government bond"],"hasTypes":["treasury note","t-bill","treasury bond","treasury bill"]},{"definition":"the federal department that collects revenue and administers federal finances; the Treasury Department was created in 1789","partOfSpeech":"noun","synonyms":["department of the treasury","treasury department","united states treasury"],"typeOf":["executive department"],"hasParts":["uscb","bureau of alcohol tobacco and firearms","bureau of customs","bureau of engraving and printing","comptroller of the currency","customs bureau","customs service","financial crimes enforcement network","financial management service","fincen","internal revenue service","irs","office of intelligence support","ois","u.s. mint","united states mint","us mint","atf"]},{"definition":"the British cabinet minister responsible for economic strategy","partOfSpeech":"noun","synonyms":["first lord of the treasury"],"typeOf":["cabinet minister"],"memberOf":["british cabinet"]},{"definition":"the funds of a government or institution or individual","partOfSpeech":"noun","synonyms":["exchequer"],"typeOf":["funds","finances","cash in hand","monetary resource","pecuniary resource"],"hasTypes":["bursary","trough","public treasury","subtreasury","fisc","till"]},{"definition":"a depository (a room or building) where wealth and precious objects can be kept safely","partOfSpeech":"noun","typeOf":["depositary","depository","repository","deposit"]},{"definition":"the government department responsible for collecting and managing and spending public revenues","partOfSpeech":"noun","typeOf":["government department"]}],"syllables":{"count":3,"list":["treas","ur","y"]},"pronunciation":{"all":"'trɛʒəri"},"frequency":3.53}
