{"word":"wait","results":[{"definition":"the act of waiting (remaining inactive in one place while expecting something)","partOfSpeech":"noun","synonyms":["waiting"],"typeOf":["inactivity"],"examples":["the wait was an ordeal for him"]},{"definition":"look forward to the probable occurrence of","partOfSpeech":"verb","synonyms":["await","expect","look"],"hasTypes":["anticipate","look to","look forward","look for","hold the line","hold on","hang on","expect"],"verbGroup":["expect","anticipate"],"derivation":["waiter"],"examples":["he is waiting to be drafted"]},{"definition":"time during which some action is awaited","partOfSpeech":"noun","synonyms":["delay","hold","postponement","time lag"],"typeOf":["interruption","suspension","pause","intermission","break"],"hasTypes":["retardation","moratorium","extension"]},{"definition":"wait before acting","partOfSpeech":"verb","synonyms":["hold back","hold off"],"typeOf":["act","move"],"hasTypes":["hold out","delay"],"derivation":["waiter"]},{"definition":"serve as a waiter or waitress in a restaurant","partOfSpeech":"verb","synonyms":["waitress"],"typeOf":["work"],"derivation":["waiter"],"examples":["I'm waiting on tables at Maxim's"]},{"definition":"stay in one place and anticipate or expect something","partOfSpeech":"verb","hasTypes":["ambush","ambuscade","bushwhack","cool one's heels","kick one's heels","lie in wait","lurk","scupper","stand by","stick about","stick around","waylay"],"derivation":["waiting","waiter"],"examples":["I had to wait on line for an hour to get the tickets"]}],"syllables":{"count":1,"list":["wait"]},"pronunciation":{"all":"weɪt"},"frequency":5.91}
